tbcp_devops/__init__.py
tbcp_devops/pkgmgmt/__init__ .py
tbcp_devops/pkgmgmt/_defaults.py
tbcp_devops/pkgmgmt/changelogger.py
tbcp_devops/pkgmgmt/examples/default/CHANGELOG
tbcp_devops/pkgmgmt/examples/default/LICENSE
tbcp_devops/pkgmgmt/examples/default/README.md
tbcp_devops/pkgmgmt/examples/git/.gitignore
tbcp_devops/pkgmgmt/examples/gitlab/.gitlab-ci.yml
tbcp_devops/pkgmgmt/examples/nodejs/package.json
tbcp_devops/pkgmgmt/examples/poetry/poetry.toml
tbcp_devops/pkgmgmt/examples/poetry/pyproject.toml
tbcp_devops/pkgmgmt/examples/python/conftest.py
tbcp_devops/pkgmgmt/examples/python/setup.cfg
tbcp_devops/pkgmgmt/examples/python/setup.py
tbcp_devops/pkgmgmt/examples/typescript/package.json
tbcp_devops/pkgmgmt/examples/typescript/tsconfig.json
tbcp_devops/pkgmgmt/files_folders.py
tbcp_devops/pkgmgmt/indicator.py
tbcp_devops/pkgmgmt/py/py_setup.py
tbcp_devops/pkgmgmt/templates/CHANGELOG.j2
tbcp_devops/pkgmgmt/versioning.py
tbcp_devops/scmgmt/__init__.py
tbcp_devops/scmgmt/_defaults.py
tbcp_devops/scmgmt/_errors.py
tbcp_devops/scmgmt/branches.py
tbcp_devops/scmgmt/changes.py
tbcp_devops/scmgmt/commits.py
tbcp_devops/scmgmt/config.py
tbcp_devops/scmgmt/remotes.py
tbcp_devops/scmgmt/repository.py
tbcp_devops/scmgmt/submodule.py
tbcp_devops/scmgmt/tags.py
tbcp_devops/scmgmt/utils/__init__.py
tbcp_devops/scmgmt/utils/commits.py
tbcp_devops-1.5.1.dist-info/LICENSE
tbcp_devops-1.5.1.dist-info/WHEEL
tbcp_devops-1.5.1.dist-info/METADATA
tbcp_devops-1.5.1.dist-info/RECORD
