Metadata-Version: 2.1
Name: tbcp-devops
Version: 1.5.1
Summary: DevOps stuff for working with files, folders, project structures, sementic versioning, Git management and so on
Home-page: https://gitlab.com/the-bootcamp-project/packages/workdirpy
License: MIT
Keywords: Git,Python
Author: Bootcamp contributors
Author-email: contributors@bootcamp-project.com
Maintainer: Bootcamp contributors
Maintainer-email: contributors@bootcamp-project.com
Requires-Python: >=3.8,<4.0
Classifier: License :: OSI Approved :: MIT License
Classifier: Programming Language :: Python :: 3
Classifier: Programming Language :: Python :: 3.10
Classifier: Programming Language :: Python :: 3.8
Classifier: Programming Language :: Python :: 3.9
Classifier: Topic :: Software Development :: Build Tools
Classifier: Topic :: Software Development :: Libraries :: Python Modules
Requires-Dist: GitPython (>=3.1.24,<4.0.0)
Requires-Dist: Jinja2 (>=3.0.3,<4.0.0)
Requires-Dist: semver (>=2.13.0,<3.0.0)
Requires-Dist: toml (>=0.10.2,<0.11.0)
Project-URL: Bug Tracker, https://gitlab.com/the-bootcamp-project/packages/workdirpy/-/issues
Project-URL: Bootcamp, https://bootcamp-project.com
Project-URL: Documentation, https://gitlab.com/the-bootcamp-project/packages/workdirpy
Project-URL: Repository, https://gitlab.com/the-bootcamp-project/packages/workdirpy.git
